<?xml version="1.0" encoding="utf-8" ?>
<dwsync>
<file name="content-twirl.jpg" server="176.34.102.23//data/disk/o1/distro/002/drupal-7.18.1-dev/sites/tekno.drupalflex.com/themes/kleen_house/" local="130018607060000000" remote="130018607060000000" Dst="0" />
<file name="about-side-image.jpg" server="176.34.102.23//data/disk/o1/distro/002/drupal-7.18.1-dev/sites/tekno.drupalflex.com/themes/kleen_house/" local="130018840870000000" remote="130018840870000000" Dst="0" />
<file name="colon.jpg" server="176.34.102.23//data/disk/o1/distro/002/drupal-7.18.1-dev/sites/tekno.drupalflex.com/themes/kleen_house/" local="130018648110000000" remote="130018648110000000" Dst="0" />
<file name="Teknokleen-group-Background-image.png" server="176.34.102.23//data/disk/o1/distro/002/drupal-7.18.1-dev/sites/tekno.drupalflex.com/themes/kleen_house/" local="130017246550000000" remote="130017246550000000" Dst="0" />
<file name="youtube.png" server="176.34.102.23//data/disk/o1/distro/002/drupal-7.18.1-dev/sites/tekno.drupalflex.com/themes/kleen_house/" local="130017800630000000" remote="130017800630000000" Dst="0" />
<file name="breadcrumb-bg.jpg" server="176.34.102.23//data/disk/o1/distro/002/drupal-7.18.1-dev/sites/tekno.drupalflex.com/themes/kleen_house/" local="130018600840000000" remote="130018600840000000" Dst="0" />
<file name="facebook.png" server="176.34.102.23//data/disk/o1/distro/002/drupal-7.18.1-dev/sites/tekno.drupalflex.com/themes/kleen_house/" local="130017800700000000" remote="130017800700000000" Dst="0" />
<file name="connect-with-us-text.png" server="176.34.102.23//data/disk/o1/distro/002/drupal-7.18.1-dev/sites/tekno.drupalflex.com/themes/kleen_house/" local="130017871860000000" remote="130017871860000000" Dst="0" />
<file name="products.jpg" server="176.34.102.23//data/disk/o1/distro/002/drupal-7.18.1-dev/sites/tekno.drupalflex.com/themes/kleen_house/" local="130018885040000000" remote="130018885040000000" Dst="0" />
<file name="instagram.png" server="176.34.102.23//data/disk/o1/distro/002/drupal-7.18.1-dev/sites/tekno.drupalflex.com/themes/kleen_house/" local="130017800660000000" remote="130017800660000000" Dst="0" />
<file name="footer-bg.png" server="176.34.102.23//data/disk/o1/distro/002/drupal-7.18.1-dev/sites/tekno.drupalflex.com/themes/kleen_house/" local="130017791350000000" remote="130017791350000000" Dst="0" />
<file name="twitter.png" server="176.34.102.23//data/disk/o1/distro/002/drupal-7.18.1-dev/sites/tekno.drupalflex.com/themes/kleen_house/" local="130017800670000000" remote="130017800670000000" Dst="0" />
<file name="careers-header.jpg" server="176.34.102.23//data/disk/o1/distro/002/drupal-7.18.1-dev/sites/tekno.drupalflex.com/themes/kleen_house/" local="130018850440000000" remote="130018850440000000" Dst="0" />
<file name="arrow.gif" server="176.34.102.23//data/disk/o1/distro/002/drupal-7.18.1-dev/sites/tekno.drupalflex.com/themes/kleen_house/" local="130050828865646857" remote="130050829720000000" Dst="0" />
<file name="strategic-alliances.png" server="176.34.102.23//data/disk/o1/distro/002/drupal-7.18.1-dev/sites/tekno.drupalflex.com/themes/kleen_house/" local="130051021976195566" remote="130051032450000000" Dst="0" />
<file name="Teknokleen-group-Background-image.png" server="176.34.102.23:2412//data/disk/o1/distro/002/drupal-7.18.1-dev/sites/tekno.drupalflex.com/themes/kleen_house/" local="130017246550000000" remote="130017246550000000" Dst="0" />
<file name="footer-bg.png" server="176.34.102.23:2412//data/disk/o1/distro/002/drupal-7.18.1-dev/sites/tekno.drupalflex.com/themes/kleen_house/" local="130017791350000000" remote="130017791350000000" Dst="0" />
<file name="breadcrumb-bg.jpg" server="176.34.102.23:2412//data/disk/o1/distro/002/drupal-7.18.1-dev/sites/tekno.drupalflex.com/themes/kleen_house/" local="130018600840000000" remote="130018600840000000" Dst="0" />
<file name="colon.jpg" server="176.34.102.23:2412//data/disk/o1/distro/002/drupal-7.18.1-dev/sites/tekno.drupalflex.com/themes/kleen_house/" local="130018648110000000" remote="130018648110000000" Dst="0" />
<file name="content-twirl.jpg" server="176.34.102.23:2412//data/disk/o1/distro/002/drupal-7.18.1-dev/sites/tekno.drupalflex.com/themes/kleen_house/" local="130018607060000000" remote="130018607060000000" Dst="0" />
<file name="strategic-alliances.png" server="176.34.102.23:2412//data/disk/o1/distro/002/drupal-7.18.1-dev/sites/tekno.drupalflex.com/themes/kleen_house/" local="130051021976195566" remote="130063514290000000" Dst="0" />
<file name="products.jpg" server="176.34.102.23:2412//data/disk/o1/distro/002/drupal-7.18.1-dev/sites/tekno.drupalflex.com/themes/kleen_house/" local="130018885040000000" remote="130018885040000000" Dst="0" />
<file name="careers-header.jpg" server="176.34.102.23:2412//data/disk/o1/distro/002/drupal-7.18.1-dev/sites/tekno.drupalflex.com/themes/kleen_house/" local="130018850440000000" remote="130018850440000000" Dst="0" />
<file name="about-side-image.jpg" server="176.34.102.23:2412//data/disk/o1/distro/002/drupal-7.18.1-dev/sites/tekno.drupalflex.com/themes/kleen_house/" local="130018840870000000" remote="130018840870000000" Dst="0" />
<file name="youtube.png" server="176.34.102.23:2412//data/disk/o1/distro/002/drupal-7.18.1-dev/sites/tekno.drupalflex.com/themes/kleen_house/" local="130017800630000000" remote="130017800630000000" Dst="0" />
<file name="instagram.png" server="176.34.102.23:2412//data/disk/o1/distro/002/drupal-7.18.1-dev/sites/tekno.drupalflex.com/themes/kleen_house/" local="130017800660000000" remote="130017800660000000" Dst="0" />
<file name="linkedin.png" server="176.34.102.23:2412//data/disk/o1/distro/002/drupal-7.18.1-dev/sites/tekno.drupalflex.com/themes/kleen_house/" local="130032056990000000" remote="130063514300000000" Dst="0" />
<file name="twitter.png" server="176.34.102.23:2412//data/disk/o1/distro/002/drupal-7.18.1-dev/sites/tekno.drupalflex.com/themes/kleen_house/" local="130017800670000000" remote="130017800670000000" Dst="0" />
<file name="facebook.png" server="176.34.102.23:2412//data/disk/o1/distro/002/drupal-7.18.1-dev/sites/tekno.drupalflex.com/themes/kleen_house/" local="130017800700000000" remote="130017800700000000" Dst="0" />
<file name="connect-with-us-text.png" server="176.34.102.23:2412//data/disk/o1/distro/002/drupal-7.18.1-dev/sites/tekno.drupalflex.com/themes/kleen_house/" local="130017871860000000" remote="130017871860000000" Dst="0" />
<file name="arrow.gif" server="176.34.102.23:2412//data/disk/o1/distro/002/drupal-7.18.1-dev/sites/tekno.drupalflex.com/themes/kleen_house/" local="130050828865646857" remote="130063514310000000" Dst="0" />
<file name="MAD-footer-logo.png" server="176.34.102.23:2412//data/disk/o1/distro/002/drupal-7.18.1-dev/sites/tekno.drupalflex.com/themes/kleen_house/" local="130063553944065874" remote="130063557130000000" Dst="0" />
</dwsync>